[
  {
    "email": "hasiniainahasina1@gmail.com",
    "password": "Finoana123.",
    "platform": "tronpick",
    "proxyIndex": 0,
    "enabled": true,
    "cookies": [
      {
        "name": "remember_token",
        "value": "4fd02687cbd1a109eb7ac1a69ac7db3e",
        "domain": "tronpick.io",
        "path": "/",
        "expires": 1779476108.547643,
        "size": 46,
        "httpOnly": false,
        "secure": false,
        "session": false,
        "priority": "Medium",
        "sourceScheme": "Secure"
      },
      {
        "name": "fp",
        "value": "0bX7PVew13MOQQNt",
        "domain": "tronpick.io",
        "path": "/",
        "expires": 1808420076,
        "size": 18,
        "httpOnly": false,
        "secure": false,
        "session": false,
        "priority": "Medium",
        "sourceScheme": "Secure"
      },
      {
        "name": "user_session",
        "value": "pbv2q0fn0tgftquo3acp42hv7ep7h7f2",
        "domain": "tronpick.io",
        "path": "/",
        "expires": 1776970510.301742,
        "size": 44,
        "httpOnly": true,
        "secure": false,
        "session": false,
        "priority": "Medium",
        "sourceScheme": "Secure"
      },
      {
        "name": "_ga",
        "value": "GA1.1.1891693018.1776884077",
        "domain": ".tronpick.io",
        "path": "/",
        "expires": 1811444109.887654,
        "size": 30,
        "httpOnly": false,
        "secure": false,
        "session": false,
        "priority": "Medium",
        "sourceScheme": "Secure"
      },
      {
        "name": "csrf_cookie_name",
        "value": "5aac4854d60dbf720ee1bf7a314b11b7",
        "domain": "tronpick.io",
        "path": "/",
        "expires": 1776891310.301648,
        "size": 48,
        "httpOnly": false,
        "secure": false,
        "session": false,
        "priority": "Medium",
        "sourceScheme": "Secure"
      },
      {
        "name": "g_state",
        "value": "{\"i_l\":0,\"i_ll\":1776884111021,\"i_b\":\"J7kpEJZcoSQMX+XnPdY7lMJbrdVYWRBgGKm66FubPvc\",\"i_e\":{\"enable_itp_optimization\":0},\"i_et\":1776884077933}",
        "domain": "tronpick.io",
        "path": "/",
        "expires": 1792436111,
        "size": 146,
        "httpOnly": false,
        "secure": false,
        "session": false,
        "priority": "Medium",
        "sourceScheme": "Secure"
      },
      {
        "name": "_ga_B22HX5LGBP",
        "value": "GS2.1.s1776884077$o1$g1$t1776884109$j28$l0$h0",
        "domain": ".tronpick.io",
        "path": "/",
        "expires": 1811444109.89508,
        "size": 59,
        "httpOnly": false,
        "secure": false,
        "session": false,
        "priority": "Medium",
        "sourceScheme": "Secure"
      }
    ],
    "cookiesStatus": "valid",
    "lastClaim": 1776884117550,
    "timer": 1
  }
]