[
  {
    "email": "hasiniainahasina1@gmail.com",
    "password": "Finoana123.",
    "timer": 60,
    "platform": "tronpick",
    "proxy": null,
    "enabled": true,
    "cookiesStatus": "valid",
    "lastClaim": 1776439261449,
    "cookies": [
      {
        "name": "remember_token",
        "value": "8ea5310b54a46a652c4d4f2173dd3321",
        "domain": "tronpick.io",
        "path": "/",
        "expires": 1779059454.731795,
        "size": 46,
        "httpOnly": false,
        "secure": false,
        "session": false,
        "priority": "Medium",
        "sourceScheme": "Secure"
      },
      {
        "name": "fp",
        "value": "Et3blJpy406JvhDD",
        "domain": "tronpick.io",
        "path": "/",
        "expires": 1808003423,
        "size": 18,
        "httpOnly": false,
        "secure": false,
        "session": false,
        "priority": "Medium",
        "sourceScheme": "Secure"
      },
      {
        "name": "user_session",
        "value": "kb28ntifejatrie81lg1qksjfk35qqnr",
        "domain": "tronpick.io",
        "path": "/",
        "expires": 1776553856.426474,
        "size": 44,
        "httpOnly": true,
        "secure": false,
        "session": false,
        "priority": "Medium",
        "sourceScheme": "Secure"
      },
      {
        "name": "_ga",
        "value": "GA1.1.796798934.1776467423",
        "domain": ".tronpick.io",
        "path": "/",
        "expires": 1811027456.073759,
        "size": 29,
        "httpOnly": false,
        "secure": false,
        "session": false,
        "priority": "Medium",
        "sourceScheme": "Secure"
      },
      {
        "name": "g_state",
        "value": "{\"i_l\":0,\"i_ll\":1776467456981,\"i_b\":\"+AErBEqDForGuJfe4BNXx+t5UN2XRTcqQmiKC6LKz4M\",\"i_e\":{\"enable_itp_optimization\":0},\"i_et\":1776467423807}",
        "domain": "tronpick.io",
        "path": "/",
        "expires": 1792019456,
        "size": 146,
        "httpOnly": false,
        "secure": false,
        "session": false,
        "priority": "Medium",
        "sourceScheme": "Secure"
      },
      {
        "name": "_ga_B22HX5LGBP",
        "value": "GS2.1.s1776467423$o1$g1$t1776467456$j27$l0$h0",
        "domain": ".tronpick.io",
        "path": "/",
        "expires": 1811027456.082365,
        "size": 59,
        "httpOnly": false,
        "secure": false,
        "session": false,
        "priority": "Medium",
        "sourceScheme": "Secure"
      },
      {
        "name": "csrf_cookie_name",
        "value": "95b3ed431d51f569602e2d613ce62b2d",
        "domain": "tronpick.io",
        "path": "/",
        "expires": 1776474656.426384,
        "size": 48,
        "httpOnly": false,
        "secure": false,
        "session": false,
        "priority": "Medium",
        "sourceScheme": "Secure"
      }
    ]
  },
  {
    "email": "rivoniainafinoana123@gmail.com",
    "password": "Finoana123.",
    "timer": 60,
    "platform": "tronpick",
    "proxy": null,
    "enabled": true,
    "cookiesStatus": "valid",
    "lastClaim": 1776444488674,
    "cookies": [
      {
        "name": "csrf_cookie_name",
        "value": "3dbb19b5edf86772e3620e1ea6e644be",
        "domain": "tronpick.io",
        "path": "/",
        "expires": 1776474849.633189,
        "size": 48,
        "httpOnly": false,
        "secure": false,
        "session": false,
        "priority": "Medium",
        "sourceScheme": "Secure"
      },
      {
        "name": "_ga",
        "value": "GA1.1.1491602445.1776467616",
        "domain": ".tronpick.io",
        "path": "/",
        "expires": 1811027649.405675,
        "size": 30,
        "httpOnly": false,
        "secure": false,
        "session": false,
        "priority": "Medium",
        "sourceScheme": "Secure"
      },
      {
        "name": "user_session",
        "value": "dntv8p4i6ejlls70rnulo342u90551f7",
        "domain": "tronpick.io",
        "path": "/",
        "expires": 1776554049.633256,
        "size": 44,
        "httpOnly": true,
        "secure": false,
        "session": false,
        "priority": "Medium",
        "sourceScheme": "Secure"
      },
      {
        "name": "fp",
        "value": "9QRicSEeKUi4lbO7",
        "domain": "tronpick.io",
        "path": "/",
        "expires": 1808003616,
        "size": 18,
        "httpOnly": false,
        "secure": false,
        "session": false,
        "priority": "Medium",
        "sourceScheme": "Secure"
      },
      {
        "name": "_ga_B22HX5LGBP",
        "value": "GS2.1.s1776467616$o1$g1$t1776467649$j27$l0$h0",
        "domain": ".tronpick.io",
        "path": "/",
        "expires": 1811027649.42456,
        "size": 59,
        "httpOnly": false,
        "secure": false,
        "session": false,
        "priority": "Medium",
        "sourceScheme": "Secure"
      },
      {
        "name": "g_state",
        "value": "{\"i_l\":0,\"i_ll\":1776467650302,\"i_b\":\"EO9HgNSI0A+QcmBMoIUCBV4vgF8rNx9868q7rRs6k/A\",\"i_e\":{\"enable_itp_optimization\":23},\"i_et\":1776467616857}",
        "domain": "tronpick.io",
        "path": "/",
        "expires": 1792019650,
        "size": 147,
        "httpOnly": false,
        "secure": false,
        "session": false,
        "priority": "Medium",
        "sourceScheme": "Secure"
      },
      {
        "name": "remember_token",
        "value": "54e093a6d021fa9f86b32926a0ffa5b4",
        "domain": "tronpick.io",
        "path": "/",
        "expires": 1779059648.033032,
        "size": 46,
        "httpOnly": false,
        "secure": false,
        "session": false,
        "priority": "Medium",
        "sourceScheme": "Secure"
      }
    ]
  }
]